tally_token/__init__.py
tally_token/__main__.py
tally_token/_version.py
tally_token-0.6.2.dist-info/LICENSE
tally_token-0.6.2.dist-info/METADATA
tally_token-0.6.2.dist-info/WHEEL
tally_token-0.6.2.dist-info/top_level.txt
tally_token-0.6.2.dist-info/RECORD
