Metadata-Version: 2.2
Name: tally-token
Version: 0.6.2
Summary: A library to split data into tokens
Author-email: Yui KITSU <kitsuyui+github@kitsuyui.com>
License: Copyright 2023-2025 Kitsu Yui
Project-URL: Homepage, https://github.com/kitsuyui/python-tally-token
Classifier: Development Status :: 3 - Alpha
Classifier: License :: OSI Approved :: BSD License
Classifier: Topic :: Security :: Cryptography
Classifier: Programming Language :: Python :: 3.9
Classifier: Programming Language :: Python :: 3.10
Classifier: Programming Language :: Python :: 3.11
Classifier: Programming Language :: Python :: 3.12
Classifier: Programming Language :: Python :: 3.13
Classifier: Intended Audience :: Developers
Requires-Python: >=3.9
License-File: LICENSE
